cloneai/__init__.py
cloneai-1.0.0.dist-info/licenses/LICENSE
cloneai-1.0.0.dist-info/METADATA
cloneai-1.0.0.dist-info/WHEEL
cloneai-1.0.0.dist-info/top_level.txt
cloneai-1.0.0.dist-info/RECORD
